getchoice/__init__.py
getchoice/getchoice.py
getchoice-1.2.0.dist-info/LICENSE
getchoice-1.2.0.dist-info/METADATA
getchoice-1.2.0.dist-info/WHEEL
getchoice-1.2.0.dist-info/RECORD
