Metadata-Version: 2.1
Name: getchoice
Version: 1.2.0
Summary: Simple, extensible user selection interface for CLI applications
Home-page: https://github.com/keagud/getchoice
License: 0BSD
Author: Keaton Guderian
Author-email: keagud@protonmail.com
Requires-Python: >=3.8,<4
Classifier: License :: OSI Approved :: BSD License
Classifier: License :: Other/Proprietary License
Classifier: Natural Language :: English
Classifier: Programming Language :: Python :: 3
Classifier: Programming Language :: Python :: 3.8
Classifier: Programming Language :: Python :: 3.9
Classifier: Programming Language :: Python :: 3.10
Classifier: Programming Language :: Python :: 3.11
Classifier: Programming Language :: Python :: 3
Classifier: Programming Language :: Python :: 3.10
Classifier: Programming Language :: Python :: 3.11
Classifier: Programming Language :: Python :: 3.8
Classifier: Programming Language :: Python :: 3.9
Requires-Dist: getkey (>=0.6.5,<0.7.0)
Requires-Dist: prompt-toolkit (>=3.0.38,<4.0.0)
